README.rst
setup.py
syntrans/__init__.py
syntrans/synsets.py
syntrans/trans.py
syntrans/utils.py
syntrans.egg-info/PKG-INFO
syntrans.egg-info/SOURCES.txt
syntrans.egg-info/dependency_links.txt
syntrans.egg-info/entry_points.txt
syntrans.egg-info/not-zip-safe
syntrans.egg-info/requires.txt
syntrans.egg-info/top_level.txt