Metadata-Version: 2.1
Name: syntrans
Version: 0.5.0
Summary: This is a simple engine for language-indepdent document (LID, based on ideas on definitionary.com).
Home-page: https://github.com/wefindx/synsets
Author: Mindey
Author-email: ~@mindey.com
License: MIT
Platform: UNKNOWN
Provides-Extra: test
